obhavouzbek/__init__.py
obhavouzbek-0.0.1.dist-info/METADATA
obhavouzbek-0.0.1.dist-info/WHEEL
obhavouzbek-0.0.1.dist-info/top_level.txt
obhavouzbek-0.0.1.dist-info/RECORD
