Metadata-Version: 2.1
Name: obhavouzbek
Version: 0.0.1
Summary: Ushbu kutubxona obhavoni bilish uchun ishlatiladi
Author: Hikmatullayev Islombek
Author-email: gimlerpro8899@gmail.com
